{
  "name": "Template Ioshield and MTConnect",
  "description": "Description",
  "general": {
    "manufacturer": "DMGMORI",
    "serialNumber": "12345678901",
    "model": "CMX 50 U",
    "control": "SIEMENS SINUMERIK 840D sl"
  },
  "dataSources": [
    {
      "id": "nc",
      "name": "NC",
      "dataPoints": [
        {
          "id": "estop",
          "name": "Emergency Stop",
          "address": "DI0",
          "readFrequency": 1000
        },
        {
          "id": "redLight",
          "name": "Red Light",
          "address": "DI1",
          "readFrequency": 1000
        },
        {
          "id": "yellowLight",
          "name": "Yellow Light",
          "address": "DI2",
          "readFrequency": 1000
        },
        {
          "id": "greenLight",
          "name": "Green Light",
          "address": "DI3",
          "readFrequency": 1000
        },
        {
          "id": "blueLight",
          "name": "Blue Light",
          "address": "DI4",
          "readFrequency": 1000
        },
        {
          "id": "avail",
          "name": "Availability",
          "address": "DI5",
          "readFrequency": 1000
        }
      ],
      "protocol": "ioshield",
      "connection": null
    }
  ],
  "dataSinks": [
    {
      "id": "mtconnect",
      "name": "My MTConnect Machine",
      "dataPoints": [
        {
          "id": "estop",
          "name": "Emergency Stop",
          "type": "event",
          "map": {
            "1": "TRIGGERED",
            "0": "ARMED"
          }
        },
        {
          "id": "execution1",
          "name": "Execution",
          "type": "event",
          "map": {
            "0": "STOPPED",
            "1": "INTERRUPTED",
            "2": "READY"
          },
          "initialValue": "READY"
        },
        {
          "id": "avail",
          "name": "Availability",
          "type": "event",
          "map": {
            "1": "AVAILABLE",
            "0": "UNAVAILABLE"
          },
          "initialValue": "AVAILABLE"
        }
      ],
      "protocol": "mtconnect"
    }
  ],
  "virtualDataPoints": [],
  "mapping": [
    {
      "source": "estop",
      "target": "estop"
    },
    {
      "source": "redLight",
      "target": "execution1",
      "mapValue": "0"
    },
    {
      "source": "greenLight",
      "target": "execution1",
      "mapValue": "2"
    },
    {
      "source": "blueLight",
      "target": "execution1",
      "mapValue": "1"
    },
    {
      "source": "avail",
      "target": "avail"
    }
  ]
}
